[
  {
    "id": "0",
    "number": "1",
    "project_name": "Name project",
    "type_work": "Front-end",
    "date_start": "2020-05-05",
    "date_finish": "2020-06-22",
    "commentary": "Comment",
    "paid": "111",
    "cost": "111",
    "source": "Site",
    "status": "In progress",
    "client": "Viktor",
    "payment": "Sberbank"
  },
  {
    "id": "1",
    "number": "2",
    "project_name": "Name project 2",
    "type_work": "Back-end",
    "date_start": "2020-05-12",
    "date_finish": "2020-05-22",
    "commentary": "Comment 2",
    "paid": "222",
    "cost": "222",
    "source": "Client",
    "status": "Completed",
    "client": "Alexey",
    "payment": "Paypal"
  }
]